recognizers_suite/__init__.py
recognizers_text_suite-1.0.2a2.dist-info/METADATA
recognizers_text_suite-1.0.2a2.dist-info/WHEEL
recognizers_text_suite-1.0.2a2.dist-info/top_level.txt
recognizers_text_suite-1.0.2a2.dist-info/RECORD
