Metadata-Version: 2.1
Name: recognizers-text-suite
Version: 1.0.2a2
Summary: recognizers-text-suite README
Home-page: https://github.com/Microsoft/Recognizers-Text
Author: Microsoft
Author-email: UNKNOWN
License: MIT
Keywords: nlp,nlp-entity-extraction,entity-extraction,parser-library
Platform: UNKNOWN
Classifier: Programming Language :: Python :: 3.6
Classifier: Intended Audience :: Developers
Classifier: License :: OSI Approved :: MIT License
Classifier: Operating System :: OS Independent
Classifier: Development Status :: 3 - Alpha
Classifier: Topic :: Scientific/Engineering :: Artificial Intelligence
Requires-Dist: recognizers-text (>=1.0.2.a2)
Requires-Dist: recognizers-text-number (>=1.0.2.a2)
Requires-Dist: recognizers-text-number-with-unit (>=1.0.2.a2)
Requires-Dist: recognizers-text-date-time (>=1.0.2.a2)
Requires-Dist: recognizers-text-sequence (>=1.0.2.a2)
Requires-Dist: recognizers-text-choice (>=1.0.2.a2)
